<?xml version="1.0" encoding="UTF-8"?>
<data xmlns="http://www.woltlab.com" xmlns:xsi="http://www.w3.org/2001/XMLSchema-instance" xsi:schemaLocation="http://www.woltlab.com http://www.woltlab.com/XSD/notification-event.xsd">
	<import>
		<event>
			<name>trashed</name>
                        <objecttype>postDelete</objecttype>
			<classfile>lib/data/user/notification/event/DefaultNotificationEvent.class.php</classfile>
                        <languagecategory>wbb.postEdit.notification</languagecategory>
                        <defaultnotificationtype>userMessages</defaultnotificationtype>
                        <icon>postTrash</icon>
                        <requiresconfirmation>1</requiresconfirmation>
			<options>thread_enable_recycle_bin</options>
		</event>
		<event>
			<name>deleted</name>
                        <objecttype>postDelete</objecttype>
			<classfile>lib/data/user/notification/event/DefaultNotificationEvent.class.php</classfile>
                        <languagecategory>wbb.postEdit.notification</languagecategory>
                        <defaultnotificationtype>userMessages</defaultnotificationtype>
                        <icon>postTrash</icon>
                        <requiresconfirmation>1</requiresconfirmation>
		</event>
	</import>
</data>
